cpp_demangle.cpython-310-aarch64-linux-gnu.so
cpp_demangle2-0.1.3.dist-info/METADATA
cpp_demangle2-0.1.3.dist-info/WHEEL
cpp_demangle2-0.1.3.dist-info/top_level.txt
cpp_demangle2-0.1.3.dist-info/RECORD
cpp_demangle2-0.1.3.dist-info/licenses/LICENSE
