Metadata-Version: 2.4
Name: cpp-demangle2
Version: 0.1.3
Summary: A package for demangling C++ linker symbols
Home-page: http://github.com/untetherai/py-cpp-demangle/
Author: Untether AI
Author-email: software@untether.ai
License: MIT
Classifier: Development Status :: 3 - Alpha
Classifier: Programming Language :: Python :: 3
Classifier: Intended Audience :: Developers
Classifier: License :: OSI Approved :: MIT License
Classifier: Topic :: Software Development :: Libraries
Classifier: Topic :: Utilities
License-File: LICENSE
Dynamic: author
Dynamic: author-email
Dynamic: classifier
Dynamic: description
Dynamic: home-page
Dynamic: license
Dynamic: license-file
Dynamic: summary
